{
    "hm": [
        {
            "code": 1210963003,
            "size": "3"
        },
        {
            "code": 1210963003,
            "size": "3"
        },
        {
            "code": 1210963003,
            "size": "3"
        }
    ],
    
    "zara": [
        {
            "code": 1210963003,
            "size": "3"
        },
        {
            "code": 1210963003,
            "size": "3"
        },
        {
            "code": 1210963003,
            "size": "3"
        }
    ]
}